datadigger/__init__.py
datadigger/utils.py
datadigger-0.11.dist-info/licenses/LICENSE
datadigger-0.11.dist-info/METADATA
datadigger-0.11.dist-info/WHEEL
datadigger-0.11.dist-info/top_level.txt
datadigger-0.11.dist-info/RECORD
