Metadata-Version: 2.4
Name: datadigger
Version: 0.11
Summary: The package is geared towards automating text-related tasks and is useful for data extraction, web scraping, and text file management.
Author: Ramesh Chandra
Author-email: rameshsofter@gmail.com
Classifier: Programming Language :: Python :: 3
Classifier: License :: OSI Approved :: MIT License
Classifier: Operating System :: OS Independent
Requires-Python: >=3.6
License-File: LICENSE
Dynamic: author
Dynamic: author-email
Dynamic: classifier
Dynamic: description
Dynamic: description-content-type
Dynamic: license-file
Dynamic: requires-python
Dynamic: summary
